README.rst
setup.py
lutes/__init__.py
lutes/component.py
lutes/errors.py
lutes/manager.py
lutes/system.py
lutes.egg-info/PKG-INFO
lutes.egg-info/SOURCES.txt
lutes.egg-info/dependency_links.txt
lutes.egg-info/top_level.txt
lutes.egg-info/zip-safe