Metadata-Version: 1.1
Name: lutes
Version: 1.0.0a1
Summary: A lightweight component-entity-system engine
Home-page: https://github.com/greizgh/lutes
Author: Greizgh
Author-email: greizgh@ephax.org
License: MIT
Download-URL: https://github.com/greizgh/lutes/releases
Keywords: component entity system
Platform: UNKNOWN
Classifier: Development Status :: 3 - Alpha
Classifier: Intended Audience :: Developers
Classifier: License :: OSI Approved :: MIT License
Classifier: Programming Language :: Python :: 3
Classifier: Topic :: Software Development :: Libraries :: Python Modules
